libpyg.so
pyg_library/__init__.py
pyg_library/_triton.py
pyg_library/home.py
pyg_library/testing.py
pyg_library/ops/__init__.py
pyg_library/ops/scatter_reduce.py
pyg_library/sampler/__init__.py
pyg_library-0.2.0.dist-info/LICENSE
pyg_library-0.2.0.dist-info/LICENSE_radix_sort
pyg_library-0.2.0.dist-info/METADATA
pyg_library-0.2.0.dist-info/WHEEL
pyg_library-0.2.0.dist-info/top_level.txt
pyg_library-0.2.0.dist-info/RECORD
