Metadata-Version: 2.1
Name: pyg-library
Version: 0.2.0
Summary: Low-Level Graph Neural Network Operators for PyG
Home-page: https://github.com/pyg-team/pyg-lib
Download-URL: https://github.com/pyg-team/pyg-lib/archive/0.2.0.dev20230414+pt113cpu.tar.gz
Author: PyG Team
Author-email: team@pyg.org
Keywords: deep-learning,pytorch,geometric-deep-learning,graph-neural-networks,graph-convolutional-networks
Classifier: Development Status :: 5 - Production/Stable
Classifier: License :: OSI Approved :: MIT License
Classifier: Programming Language :: Python
Classifier: Programming Language :: Python :: 3.7
Classifier: Programming Language :: Python :: 3.8
Classifier: Programming Language :: Python :: 3.9
Classifier: Programming Language :: Python :: 3.10
Classifier: Programming Language :: Python :: 3 :: Only
Requires-Python: >=3.7
License-File: LICENSE
License-File: LICENSE_radix_sort
Provides-Extra: dev
Requires-Dist: pre-commit ; extra == 'dev'
Provides-Extra: test
Requires-Dist: pytest ; extra == 'test'
Requires-Dist: pytest-cov ; extra == 'test'
Provides-Extra: triton
Requires-Dist: triton ; extra == 'triton'
